{
    "4c7be918-3170-a864-69b6-930f37288cf7": {
        "paletteKey": "FlexLayoutCol",
        "designerReference": [
            {
                "_key": "componentLabel",
                "_value": "Column",
                "_type": "kv",
                "_attrDef": "p",
                "_useAsLabel": true
            },
            {
                "_key": "style",
                "_value": "",
                "_type": "kv",
                "_attrDef": "p"
            },
            {
                "_key": "class",
                "_value": "",
                "_type": "dav",
                "_attrDef": "p"
            },
            {
                "_key": "fxFlex",
                "_value": "",
                "_type": "kv",
                "_attrDef": "p"
            },
            {
                "_key": "fxLayoutGap",
                "_value": "",
                "_type": "kv",
                "_attrDef": "p"
            },
            {
                "_key": "wrap",
                "_value": "wrap",
                "_type": "a",
                "_attrDef": "p"
            },
            {
                "_key": "layoutAlign",
                "_value": "start",
                "_type": "a",
                "_attrDef": "p"
            },
            {
                "_key": "pLayoutAlign",
                "_value": "stretch",
                "_type": "a",
                "_attrDef": "p"
            },
            {
                "_key": "[fxShow]",
                "_value": "true",
                "_type": "kv",
                "_attrDef": "p"
            },
            {
                "_key": "[fxHide]",
                "_value": "false",
                "_type": "kv",
                "_attrDef": "p"
            }
        ],
        "c1313a3e-4b5c-9abc-92a3-8f1990d0a509": {
            "paletteKey": "NEUTRINOS_VIEW_incidentmain",
            "parentEditorKey": "4c7be918-3170-a864-69b6-930f37288cf7",
            "designerReference": [
                {
                    "_key": "componentLabel",
                    "_value": "incidentmain",
                    "_type": "kv",
                    "_attrDef": "p",
                    "_useAsLabel": true
                },
                {
                    "_key": "style",
                    "_value": "",
                    "_type": "kv",
                    "_attrDef": "p"
                },
                {
                    "_key": "class",
                    "_value": "",
                    "_type": "dav",
                    "_attrDef": "p"
                }
            ]
        },
        "19f5d402-d9c3-1599-34be-bfc65d2ee140": {
            "paletteKey": "ad-card",
            "parentEditorKey": "4c7be918-3170-a864-69b6-930f37288cf7",
            "isAdvancedComponent": true,
            "designerReference": [
                {
                    "_key": "componentLabel",
                    "_value": "Card",
                    "_type": "kv",
                    "_attrDef": "p",
                    "_useAsLabel": true
                },
                {
                    "_key": "style",
                    "_value": "height:",
                    "_type": "kv",
                    "_attrDef": "p"
                },
                {
                    "_key": "class",
                    "_value": "",
                    "_type": "dav",
                    "_attrDef": "p"
                },
                {
                    "_key": "tabindex",
                    "_value": "",
                    "_type": "kv",
                    "_attrDef": "p"
                }
            ],
            "6b47359c-2146-b94c-c0ef-e75ca0caf2d8": {
                "paletteKey": "ng-card-content",
                "parentEditorKey": "19f5d402-d9c3-1599-34be-bfc65d2ee140",
                "isAdvancedChildComponent": true,
                "designerReference": [
                    {
                        "_key": "style",
                        "_value": "",
                        "_type": "kv",
                        "_attrDef": "p"
                    },
                    {
                        "_key": "class",
                        "_value": "",
                        "_type": "dav",
                        "_attrDef": "p"
                    },
                    {
                        "_key": "align",
                        "_value": "",
                        "_type": "kv",
                        "_attrDef": "p"
                    }
                ],
                "75421290-c1f5-cd23-fff9-494c53efda6b": {
                    "paletteKey": "FlexLayoutRow",
                    "parentEditorKey": "6b47359c-2146-b94c-c0ef-e75ca0caf2d8",
                    "designerReference": [
                        {
                            "_key": "componentLabel",
                            "_value": "Row",
                            "_type": "kv",
                            "_attrDef": "p",
                            "_useAsLabel": true
                        },
                        {
                            "_key": "style",
                            "_value": "",
                            "_type": "kv",
                            "_attrDef": "p"
                        },
                        {
                            "_key": "class",
                            "_value": "",
                            "_type": "dav",
                            "_attrDef": "p"
                        },
                        {
                            "_key": "fxFlex",
                            "_value": "",
                            "_type": "kv",
                            "_attrDef": "p"
                        },
                        {
                            "_key": "fxLayoutGap",
                            "_value": "120px",
                            "_type": "kv",
                            "_attrDef": "p"
                        },
                        {
                            "_key": "wrap",
                            "_value": "wrap",
                            "_type": "a",
                            "_attrDef": "p"
                        },
                        {
                            "_key": "layoutAlign",
                            "_value": "start",
                            "_type": "a",
                            "_attrDef": "p"
                        },
                        {
                            "_key": "pLayoutAlign",
                            "_value": "stretch",
                            "_type": "a",
                            "_attrDef": "p"
                        },
                        {
                            "_key": "[fxShow]",
                            "_value": "true",
                            "_type": "kv",
                            "_attrDef": "p"
                        },
                        {
                            "_key": "[fxHide]",
                            "_value": "false",
                            "_type": "kv",
                            "_attrDef": "p"
                        }
                    ],
                    "42b20022-665e-6234-11f3-597c2a54cec3": {
                        "paletteKey": "FlexLayoutCol",
                        "parentEditorKey": "75421290-c1f5-cd23-fff9-494c53efda6b",
                        "designerReference": [
                            {
                                "_key": "componentLabel",
                                "_value": "Column",
                                "_type": "kv",
                                "_attrDef": "p",
                                "_useAsLabel": true
                            },
                            {
                                "_key": "style",
                                "_value": "",
                                "_type": "kv",
                                "_attrDef": "p"
                            },
                            {
                                "_key": "class",
                                "_value": "",
                                "_type": "dav",
                                "_attrDef": "p"
                            },
                            {
                                "_key": "fxFlex",
                                "_value": "",
                                "_type": "kv",
                                "_attrDef": "p"
                            },
                            {
                                "_key": "fxLayoutGap",
                                "_value": "30px",
                                "_type": "kv",
                                "_attrDef": "p"
                            },
                            {
                                "_key": "wrap",
                                "_value": "wrap",
                                "_type": "a",
                                "_attrDef": "p"
                            },
                            {
                                "_key": "layoutAlign",
                                "_value": "start",
                                "_type": "a",
                                "_attrDef": "p"
                            },
                            {
                                "_key": "pLayoutAlign",
                                "_value": "stretch",
                                "_type": "a",
                                "_attrDef": "p"
                            },
                            {
                                "_key": "[fxShow]",
                                "_value": "true",
                                "_type": "kv",
                                "_attrDef": "p"
                            },
                            {
                                "_key": "[fxHide]",
                                "_value": "false",
                                "_type": "kv",
                                "_attrDef": "p"
                            }
                        ],
                        "784e36e9-7b96-5735-6de7-ea7d221bf7af": {
                            "paletteKey": "NG-icon",
                            "parentEditorKey": "42b20022-665e-6234-11f3-597c2a54cec3",
                            "isCommented": "true",
                            "designerReference": [
                                {
                                    "_key": "style",
                                    "_value": "width:200px;height:200px;",
                                    "_type": "kv",
                                    "_attrDef": "p"
                                },
                                {
                                    "_key": "class",
                                    "_value": "",
                                    "_type": "dav",
                                    "_attrDef": "p"
                                },
                                {
                                    "_key": "IconName",
                                    "_value": "account_circle",
                                    "_type": "a",
                                    "_attrDef": "p",
                                    "_useAsLabel": true
                                },
                                {
                                    "_key": "[inline]",
                                    "_value": "",
                                    "_type": "kv",
                                    "_attrDef": "p"
                                },
                                {
                                    "_key": "color",
                                    "_value": "",
                                    "_type": "kv",
                                    "_attrDef": "p"
                                }
                            ]
                        },
                        "43d79fff-dd40-873c-3f88-f823398989e7": {
                            "paletteKey": "NG-image",
                            "parentEditorKey": "42b20022-665e-6234-11f3-597c2a54cec3",
                            "designerReference": [
                                {
                                    "_key": "componentLabel",
                                    "_value": "Image",
                                    "_type": "kv",
                                    "_attrDef": "p",
                                    "_useAsLabel": true
                                },
                                {
                                    "_key": "style",
                                    "_value": "margin-left: 86px;",
                                    "_type": "kv",
                                    "_attrDef": "p"
                                },
                                {
                                    "_key": "class",
                                    "_value": "",
                                    "_type": "dav",
                                    "_attrDef": "p"
                                },
                                {
                                    "_key": "imgSrc",
                                    "_value": "Web/Icons/profile.jpg",
                                    "_type": "kv",
                                    "_attrDef": "p"
                                },
                                {
                                    "_key": "alt",
                                    "_value": "",
                                    "_type": "kv",
                                    "_attrDef": "p"
                                },
                                {
                                    "_key": "[src]",
                                    "_value": "",
                                    "_type": "kv",
                                    "_attrDef": "p"
                                },
                                {
                                    "_key": "imgSecure",
                                    "_value": "",
                                    "_type": "a",
                                    "_attrDef": "p"
                                },
                                {
                                    "_key": "[collectionName]",
                                    "_value": "",
                                    "_type": "kv",
                                    "_attrDef": "p"
                                },
                                {
                                    "_key": "[imageFilter]",
                                    "_value": "",
                                    "_type": "kv",
                                    "_attrDef": "p"
                                },
                                {
                                    "_key": "width",
                                    "_value": "200px",
                                    "_type": "kv",
                                    "_attrDef": "p"
                                },
                                {
                                    "_key": "srcset",
                                    "_value": "",
                                    "_type": "kv",
                                    "_attrDef": "p"
                                },
                                {
                                    "_key": "sizes",
                                    "_value": "",
                                    "_type": "kv",
                                    "_attrDef": "p"
                                }
                            ]
                        }
                    },
                    "8511f1d6-ba32-58c8-3bb0-577601bda273": {
                        "paletteKey": "FlexLayoutCol",
                        "parentEditorKey": "75421290-c1f5-cd23-fff9-494c53efda6b",
                        "designerReference": [
                            {
                                "_key": "componentLabel",
                                "_value": "Column",
                                "_type": "kv",
                                "_attrDef": "p",
                                "_useAsLabel": true
                            },
                            {
                                "_key": "style",
                                "_value": "padding-left:20px",
                                "_type": "kv",
                                "_attrDef": "p"
                            },
                            {
                                "_key": "class",
                                "_value": "",
                                "_type": "dav",
                                "_attrDef": "p"
                            },
                            {
                                "_key": "fxFlex",
                                "_value": "",
                                "_type": "kv",
                                "_attrDef": "p"
                            },
                            {
                                "_key": "fxLayoutGap",
                                "_value": "",
                                "_type": "kv",
                                "_attrDef": "p"
                            },
                            {
                                "_key": "wrap",
                                "_value": "wrap",
                                "_type": "a",
                                "_attrDef": "p"
                            },
                            {
                                "_key": "layoutAlign",
                                "_value": "start",
                                "_type": "a",
                                "_attrDef": "p"
                            },
                            {
                                "_key": "pLayoutAlign",
                                "_value": "stretch",
                                "_type": "a",
                                "_attrDef": "p"
                            },
                            {
                                "_key": "[fxShow]",
                                "_value": "true",
                                "_type": "kv",
                                "_attrDef": "p"
                            },
                            {
                                "_key": "[fxHide]",
                                "_value": "false",
                                "_type": "kv",
                                "_attrDef": "p"
                            }
                        ],
                        "6e9ec136-6bc1-98c7-d4fb-9760c0e4ba54": {
                            "paletteKey": "Html5",
                            "parentEditorKey": "8511f1d6-ba32-58c8-3bb0-577601bda273",
                            "isAdvancedComponent": true,
                            "designerReference": [
                                {
                                    "_key": "style",
                                    "_value": "",
                                    "_type": "kv",
                                    "_attrDef": "p"
                                },
                                {
                                    "_key": "class",
                                    "_value": "",
                                    "_type": "dav",
                                    "_attrDef": "p"
                                },
                                {
                                    "_key": "htmlElement",
                                    "_value": "h2",
                                    "_type": "dav",
                                    "_attrDef": "p",
                                    "_useAsLabel": true
                                },
                                {
                                    "_key": "tagType",
                                    "_value": "h2",
                                    "_type": "a",
                                    "_attrDef": "p",
                                    "_visibility": false
                                },
                                {
                                    "_key": "name",
                                    "_value": "",
                                    "_type": "kv",
                                    "_attrDef": "p",
                                    "_visibility": false
                                },
                                {
                                    "_key": "sandbox",
                                    "_value": "",
                                    "_type": "kv",
                                    "_attrDef": "p",
                                    "_visibility": false
                                },
                                {
                                    "_key": "src",
                                    "_value": "",
                                    "_type": "kv",
                                    "_attrDef": "p",
                                    "_visibility": false
                                },
                                {
                                    "_key": "srcdoc",
                                    "_value": "",
                                    "_type": "kv",
                                    "_attrDef": "p",
                                    "_visibility": false
                                },
                                {
                                    "_key": "width",
                                    "_value": "",
                                    "_type": "kv",
                                    "_attrDef": "p",
                                    "_visibility": false
                                },
                                {
                                    "_key": "[autoplay]",
                                    "_value": "",
                                    "_type": "kv",
                                    "_attrDef": "p",
                                    "_visibility": false
                                },
                                {
                                    "_key": "[loop]",
                                    "_value": "",
                                    "_type": "kv",
                                    "_attrDef": "p",
                                    "_visibility": false
                                },
                                {
                                    "_key": "data",
                                    "_value": "",
                                    "_type": "kv",
                                    "_attrDef": "p",
                                    "_visibility": false
                                },
                                {
                                    "_key": "audioSource",
                                    "_value": [],
                                    "_type": "a",
                                    "_attrDef": "p",
                                    "_visibility": false
                                },
                                {
                                    "_key": "videoSource",
                                    "_value": [],
                                    "_type": "a",
                                    "_attrDef": "p",
                                    "_visibility": false
                                },
                                {
                                    "_key": "audioDatasource",
                                    "_value": "",
                                    "_type": "a",
                                    "_attrDef": "p",
                                    "_visibility": false
                                },
                                {
                                    "_key": "audioSrc",
                                    "_value": "",
                                    "_type": "a",
                                    "_attrDef": "p",
                                    "_visibility": false
                                },
                                {
                                    "_key": "audioType",
                                    "_value": "",
                                    "_type": "a",
                                    "_attrDef": "p",
                                    "_visibility": false
                                },
                                {
                                    "_key": "videoDatasource",
                                    "_value": "",
                                    "_type": "a",
                                    "_attrDef": "p",
                                    "_visibility": false
                                },
                                {
                                    "_key": "videoSrc",
                                    "_value": "",
                                    "_type": "a",
                                    "_attrDef": "p",
                                    "_visibility": false
                                },
                                {
                                    "_key": "videoType",
                                    "_value": "",
                                    "_type": "a",
                                    "_attrDef": "p",
                                    "_visibility": false
                                },
                                {
                                    "_key": "(audioplay)",
                                    "_value": "",
                                    "_type": "a",
                                    "_attrDef": "p",
                                    "_visibility": false
                                },
                                {
                                    "_key": "(videoplay)",
                                    "_value": "",
                                    "_type": "a",
                                    "_attrDef": "p",
                                    "_visibility": false
                                },
                                {
                                    "_key": "(audiopause)",
                                    "_value": "",
                                    "_type": "kv",
                                    "_attrDef": "p",
                                    "_visibility": false
                                },
                                {
                                    "_key": "(videopause)",
                                    "_value": "",
                                    "_type": "kv",
                                    "_attrDef": "p",
                                    "_visibility": false
                                },
                                {
                                    "_key": "(audioended)",
                                    "_value": "",
                                    "_type": "kv",
                                    "_attrDef": "p",
                                    "_visibility": false
                                },
                                {
                                    "_key": "(videoended)",
                                    "_value": "",
                                    "_type": "kv",
                                    "_attrDef": "p",
                                    "_visibility": false
                                }
                            ],
                            "81820f71-fd69-8925-b863-7c3ccc2198ca": {
                                "paletteKey": "html-editor",
                                "parentEditorKey": "6e9ec136-6bc1-98c7-d4fb-9760c0e4ba54",
                                "isAdvancedChildComponent": true,
                                "designerReference": [
                                    {
                                        "_key": "style",
                                        "_value": "",
                                        "_type": "kv",
                                        "_attrDef": "p"
                                    },
                                    {
                                        "_key": "class",
                                        "_value": "",
                                        "_type": "dav",
                                        "_attrDef": "p"
                                    },
                                    {
                                        "_key": "html",
                                        "_value": "User Profile",
                                        "_type": "a",
                                        "_attrDef": "p"
                                    }
                                ]
                            }
                        },
                        "6415ce06-8a13-4821-c866-6d826d246769": {
                            "paletteKey": "Html5",
                            "parentEditorKey": "8511f1d6-ba32-58c8-3bb0-577601bda273",
                            "isAdvancedComponent": true,
                            "designerReference": [
                                {
                                    "_key": "style",
                                    "_value": "",
                                    "_type": "kv",
                                    "_attrDef": "p"
                                },
                                {
                                    "_key": "class",
                                    "_value": "",
                                    "_type": "dav",
                                    "_attrDef": "p"
                                },
                                {
                                    "_key": "htmlElement",
                                    "_value": "div",
                                    "_type": "dav",
                                    "_attrDef": "p",
                                    "_useAsLabel": true
                                },
                                {
                                    "_key": "tagType",
                                    "_value": "",
                                    "_type": "a",
                                    "_attrDef": "p",
                                    "_visibility": false
                                },
                                {
                                    "_key": "name",
                                    "_value": "",
                                    "_type": "kv",
                                    "_attrDef": "p",
                                    "_visibility": false
                                },
                                {
                                    "_key": "sandbox",
                                    "_value": "",
                                    "_type": "kv",
                                    "_attrDef": "p",
                                    "_visibility": false
                                },
                                {
                                    "_key": "src",
                                    "_value": "",
                                    "_type": "kv",
                                    "_attrDef": "p",
                                    "_visibility": false
                                },
                                {
                                    "_key": "srcdoc",
                                    "_value": "",
                                    "_type": "kv",
                                    "_attrDef": "p",
                                    "_visibility": false
                                },
                                {
                                    "_key": "width",
                                    "_value": "",
                                    "_type": "kv",
                                    "_attrDef": "p",
                                    "_visibility": false
                                },
                                {
                                    "_key": "[autoplay]",
                                    "_value": "",
                                    "_type": "kv",
                                    "_attrDef": "p",
                                    "_visibility": false
                                },
                                {
                                    "_key": "[loop]",
                                    "_value": "",
                                    "_type": "kv",
                                    "_attrDef": "p",
                                    "_visibility": false
                                },
                                {
                                    "_key": "data",
                                    "_value": "",
                                    "_type": "kv",
                                    "_attrDef": "p",
                                    "_visibility": false
                                },
                                {
                                    "_key": "audioSource",
                                    "_value": [],
                                    "_type": "a",
                                    "_attrDef": "p",
                                    "_visibility": false
                                },
                                {
                                    "_key": "videoSource",
                                    "_value": [],
                                    "_type": "a",
                                    "_attrDef": "p",
                                    "_visibility": false
                                },
                                {
                                    "_key": "audioDatasource",
                                    "_value": "",
                                    "_type": "a",
                                    "_attrDef": "p",
                                    "_visibility": false
                                },
                                {
                                    "_key": "audioSrc",
                                    "_value": "",
                                    "_type": "a",
                                    "_attrDef": "p",
                                    "_visibility": false
                                },
                                {
                                    "_key": "audioType",
                                    "_value": "",
                                    "_type": "a",
                                    "_attrDef": "p",
                                    "_visibility": false
                                },
                                {
                                    "_key": "videoDatasource",
                                    "_value": "",
                                    "_type": "a",
                                    "_attrDef": "p",
                                    "_visibility": false
                                },
                                {
                                    "_key": "videoSrc",
                                    "_value": "",
                                    "_type": "a",
                                    "_attrDef": "p",
                                    "_visibility": false
                                },
                                {
                                    "_key": "videoType",
                                    "_value": "",
                                    "_type": "a",
                                    "_attrDef": "p",
                                    "_visibility": false
                                },
                                {
                                    "_key": "(audioplay)",
                                    "_value": "",
                                    "_type": "a",
                                    "_attrDef": "p",
                                    "_visibility": false
                                },
                                {
                                    "_key": "(videoplay)",
                                    "_value": "",
                                    "_type": "a",
                                    "_attrDef": "p",
                                    "_visibility": false
                                },
                                {
                                    "_key": "(audiopause)",
                                    "_value": "",
                                    "_type": "kv",
                                    "_attrDef": "p",
                                    "_visibility": false
                                },
                                {
                                    "_key": "(videopause)",
                                    "_value": "",
                                    "_type": "kv",
                                    "_attrDef": "p",
                                    "_visibility": false
                                },
                                {
                                    "_key": "(audioended)",
                                    "_value": "",
                                    "_type": "kv",
                                    "_attrDef": "p",
                                    "_visibility": false
                                },
                                {
                                    "_key": "(videoended)",
                                    "_value": "",
                                    "_type": "kv",
                                    "_attrDef": "p",
                                    "_visibility": false
                                }
                            ],
                            "f9608bec-8ed4-c38d-ed65-3b4e6926cac2": {
                                "paletteKey": "html-editor",
                                "parentEditorKey": "6415ce06-8a13-4821-c866-6d826d246769",
                                "isAdvancedChildComponent": true,
                                "designerReference": [
                                    {
                                        "_key": "style",
                                        "_value": "",
                                        "_type": "kv",
                                        "_attrDef": "p"
                                    },
                                    {
                                        "_key": "class",
                                        "_value": "",
                                        "_type": "dav",
                                        "_attrDef": "p"
                                    },
                                    {
                                        "_key": "html",
                                        "_value": "<h4>User Name  </h4><p>{{name}}</p>",
                                        "_type": "a",
                                        "_attrDef": "p"
                                    }
                                ]
                            }
                        },
                        "d7230249-4806-caeb-e6d4-d2445d54d5d3": {
                            "paletteKey": "Html5",
                            "parentEditorKey": "8511f1d6-ba32-58c8-3bb0-577601bda273",
                            "isAdvancedComponent": true,
                            "designerReference": [
                                {
                                    "_key": "style",
                                    "_value": "",
                                    "_type": "kv",
                                    "_attrDef": "p"
                                },
                                {
                                    "_key": "class",
                                    "_value": "",
                                    "_type": "dav",
                                    "_attrDef": "p"
                                },
                                {
                                    "_key": "htmlElement",
                                    "_value": "div",
                                    "_type": "dav",
                                    "_attrDef": "p",
                                    "_useAsLabel": true
                                },
                                {
                                    "_key": "tagType",
                                    "_value": "",
                                    "_type": "a",
                                    "_attrDef": "p",
                                    "_visibility": false
                                },
                                {
                                    "_key": "name",
                                    "_value": "",
                                    "_type": "kv",
                                    "_attrDef": "p",
                                    "_visibility": false
                                },
                                {
                                    "_key": "sandbox",
                                    "_value": "",
                                    "_type": "kv",
                                    "_attrDef": "p",
                                    "_visibility": false
                                },
                                {
                                    "_key": "src",
                                    "_value": "",
                                    "_type": "kv",
                                    "_attrDef": "p",
                                    "_visibility": false
                                },
                                {
                                    "_key": "srcdoc",
                                    "_value": "",
                                    "_type": "kv",
                                    "_attrDef": "p",
                                    "_visibility": false
                                },
                                {
                                    "_key": "width",
                                    "_value": "",
                                    "_type": "kv",
                                    "_attrDef": "p",
                                    "_visibility": false
                                },
                                {
                                    "_key": "[autoplay]",
                                    "_value": "",
                                    "_type": "kv",
                                    "_attrDef": "p",
                                    "_visibility": false
                                },
                                {
                                    "_key": "[loop]",
                                    "_value": "",
                                    "_type": "kv",
                                    "_attrDef": "p",
                                    "_visibility": false
                                },
                                {
                                    "_key": "data",
                                    "_value": "",
                                    "_type": "kv",
                                    "_attrDef": "p",
                                    "_visibility": false
                                },
                                {
                                    "_key": "audioSource",
                                    "_value": [],
                                    "_type": "a",
                                    "_attrDef": "p",
                                    "_visibility": false
                                },
                                {
                                    "_key": "videoSource",
                                    "_value": [],
                                    "_type": "a",
                                    "_attrDef": "p",
                                    "_visibility": false
                                },
                                {
                                    "_key": "audioDatasource",
                                    "_value": "",
                                    "_type": "a",
                                    "_attrDef": "p",
                                    "_visibility": false
                                },
                                {
                                    "_key": "audioSrc",
                                    "_value": "",
                                    "_type": "a",
                                    "_attrDef": "p",
                                    "_visibility": false
                                },
                                {
                                    "_key": "audioType",
                                    "_value": "",
                                    "_type": "a",
                                    "_attrDef": "p",
                                    "_visibility": false
                                },
                                {
                                    "_key": "videoDatasource",
                                    "_value": "",
                                    "_type": "a",
                                    "_attrDef": "p",
                                    "_visibility": false
                                },
                                {
                                    "_key": "videoSrc",
                                    "_value": "",
                                    "_type": "a",
                                    "_attrDef": "p",
                                    "_visibility": false
                                },
                                {
                                    "_key": "videoType",
                                    "_value": "",
                                    "_type": "a",
                                    "_attrDef": "p",
                                    "_visibility": false
                                },
                                {
                                    "_key": "(audioplay)",
                                    "_value": "",
                                    "_type": "a",
                                    "_attrDef": "p",
                                    "_visibility": false
                                },
                                {
                                    "_key": "(videoplay)",
                                    "_value": "",
                                    "_type": "a",
                                    "_attrDef": "p",
                                    "_visibility": false
                                },
                                {
                                    "_key": "(audiopause)",
                                    "_value": "",
                                    "_type": "kv",
                                    "_attrDef": "p",
                                    "_visibility": false
                                },
                                {
                                    "_key": "(videopause)",
                                    "_value": "",
                                    "_type": "kv",
                                    "_attrDef": "p",
                                    "_visibility": false
                                },
                                {
                                    "_key": "(audioended)",
                                    "_value": "",
                                    "_type": "kv",
                                    "_attrDef": "p",
                                    "_visibility": false
                                },
                                {
                                    "_key": "(videoended)",
                                    "_value": "",
                                    "_type": "kv",
                                    "_attrDef": "p",
                                    "_visibility": false
                                }
                            ],
                            "95b18274-6195-aa0a-8aad-360e23bc9f17": {
                                "paletteKey": "html-editor",
                                "parentEditorKey": "d7230249-4806-caeb-e6d4-d2445d54d5d3",
                                "isAdvancedChildComponent": true,
                                "designerReference": [
                                    {
                                        "_key": "style",
                                        "_value": "",
                                        "_type": "kv",
                                        "_attrDef": "p"
                                    },
                                    {
                                        "_key": "class",
                                        "_value": "",
                                        "_type": "dav",
                                        "_attrDef": "p"
                                    },
                                    {
                                        "_key": "html",
                                        "_value": "<p><h4>User mail</h4>{{username}}</p><br>",
                                        "_type": "a",
                                        "_attrDef": "p"
                                    }
                                ]
                            }
                        },
                        "e944475c-cd62-2a13-b7b6-b879a4e9d01a": {
                            "paletteKey": "Html5",
                            "parentEditorKey": "8511f1d6-ba32-58c8-3bb0-577601bda273",
                            "isAdvancedComponent": true,
                            "designerReference": [
                                {
                                    "_key": "style",
                                    "_value": "",
                                    "_type": "kv",
                                    "_attrDef": "p"
                                },
                                {
                                    "_key": "class",
                                    "_value": "",
                                    "_type": "dav",
                                    "_attrDef": "p"
                                },
                                {
                                    "_key": "htmlElement",
                                    "_value": "div",
                                    "_type": "dav",
                                    "_attrDef": "p",
                                    "_useAsLabel": true
                                },
                                {
                                    "_key": "tagType",
                                    "_value": "",
                                    "_type": "a",
                                    "_attrDef": "p",
                                    "_visibility": false
                                },
                                {
                                    "_key": "name",
                                    "_value": "",
                                    "_type": "kv",
                                    "_attrDef": "p",
                                    "_visibility": false
                                },
                                {
                                    "_key": "sandbox",
                                    "_value": "",
                                    "_type": "kv",
                                    "_attrDef": "p",
                                    "_visibility": false
                                },
                                {
                                    "_key": "src",
                                    "_value": "",
                                    "_type": "kv",
                                    "_attrDef": "p",
                                    "_visibility": false
                                },
                                {
                                    "_key": "srcdoc",
                                    "_value": "",
                                    "_type": "kv",
                                    "_attrDef": "p",
                                    "_visibility": false
                                },
                                {
                                    "_key": "width",
                                    "_value": "",
                                    "_type": "kv",
                                    "_attrDef": "p",
                                    "_visibility": false
                                },
                                {
                                    "_key": "[autoplay]",
                                    "_value": "",
                                    "_type": "kv",
                                    "_attrDef": "p",
                                    "_visibility": false
                                },
                                {
                                    "_key": "[loop]",
                                    "_value": "",
                                    "_type": "kv",
                                    "_attrDef": "p",
                                    "_visibility": false
                                },
                                {
                                    "_key": "data",
                                    "_value": "",
                                    "_type": "kv",
                                    "_attrDef": "p",
                                    "_visibility": false
                                },
                                {
                                    "_key": "audioSource",
                                    "_value": [],
                                    "_type": "a",
                                    "_attrDef": "p",
                                    "_visibility": false
                                },
                                {
                                    "_key": "videoSource",
                                    "_value": [],
                                    "_type": "a",
                                    "_attrDef": "p",
                                    "_visibility": false
                                },
                                {
                                    "_key": "audioDatasource",
                                    "_value": "",
                                    "_type": "a",
                                    "_attrDef": "p",
                                    "_visibility": false
                                },
                                {
                                    "_key": "audioSrc",
                                    "_value": "",
                                    "_type": "a",
                                    "_attrDef": "p",
                                    "_visibility": false
                                },
                                {
                                    "_key": "audioType",
                                    "_value": "",
                                    "_type": "a",
                                    "_attrDef": "p",
                                    "_visibility": false
                                },
                                {
                                    "_key": "videoDatasource",
                                    "_value": "",
                                    "_type": "a",
                                    "_attrDef": "p",
                                    "_visibility": false
                                },
                                {
                                    "_key": "videoSrc",
                                    "_value": "",
                                    "_type": "a",
                                    "_attrDef": "p",
                                    "_visibility": false
                                },
                                {
                                    "_key": "videoType",
                                    "_value": "",
                                    "_type": "a",
                                    "_attrDef": "p",
                                    "_visibility": false
                                },
                                {
                                    "_key": "(audioplay)",
                                    "_value": "",
                                    "_type": "a",
                                    "_attrDef": "p",
                                    "_visibility": false
                                },
                                {
                                    "_key": "(videoplay)",
                                    "_value": "",
                                    "_type": "a",
                                    "_attrDef": "p",
                                    "_visibility": false
                                },
                                {
                                    "_key": "(audiopause)",
                                    "_value": "",
                                    "_type": "kv",
                                    "_attrDef": "p",
                                    "_visibility": false
                                },
                                {
                                    "_key": "(videopause)",
                                    "_value": "",
                                    "_type": "kv",
                                    "_attrDef": "p",
                                    "_visibility": false
                                },
                                {
                                    "_key": "(audioended)",
                                    "_value": "",
                                    "_type": "kv",
                                    "_attrDef": "p",
                                    "_visibility": false
                                },
                                {
                                    "_key": "(videoended)",
                                    "_value": "",
                                    "_type": "kv",
                                    "_attrDef": "p",
                                    "_visibility": false
                                }
                            ],
                            "ffc2f06c-cb6d-adce-52f5-9d3bb16cc7fc": {
                                "paletteKey": "html-editor",
                                "parentEditorKey": "e944475c-cd62-2a13-b7b6-b879a4e9d01a",
                                "isAdvancedChildComponent": true,
                                "designerReference": [
                                    {
                                        "_key": "style",
                                        "_value": "",
                                        "_type": "kv",
                                        "_attrDef": "p"
                                    },
                                    {
                                        "_key": "class",
                                        "_value": "",
                                        "_type": "dav",
                                        "_attrDef": "p"
                                    },
                                    {
                                        "_key": "html",
                                        "_value": "<h4>Role  </h4><p>{{role}}</p>",
                                        "_type": "a",
                                        "_attrDef": "p"
                                    }
                                ]
                            }
                        }
                    }
                }
            }
        }
    }
}
